[
  {
    "id": "ich-e6-r3-term-001",
    "entry_type": "translation_mapping",
    "term_en": "access control",
    "preferred_label_fi": "käyttöoikeuksien hallinta",
    "definition_fi": null,
    "definition_en": null,
    "source": "fimea_en_fi_terminology",
    "source_page_fi": 106,
    "official_ich_glossary_entry": false
  },
  {
    "id": "ich-e6-r3-term-002",
    "entry_type": "translation_mapping",
    "term_en": "activity / activities",
    "preferred_label_fi": "toimi / toimet (sisältää tehtävät, vastuut ja toiminnot)",
    "definition_fi": null,
    "definition_en": null,
    "source": "fimea_en_fi_terminology",
    "source_page_fi": 106,
    "official_ich_glossary_entry": false
  },
  {
    "id": "ich-e6-r3-term-003",
    "entry_type": "translation_mapping",
    "term_en": "adaptability",
    "preferred_label_fi": "joustavuus, mukautuvuus",
    "definition_fi": null,
    "definition_en": null,
    "source": "fimea_en_fi_terminology",
    "source_page_fi": 106,
    "official_ich_glossary_entry": false
  },
  {
    "id": "ich-e6-r3-term-004",
    "entry_type": "translation_mapping",
    "term_en": "adjudication committee",
    "preferred_label_fi": "arviointitoimikunta",
    "definition_fi": null,
    "definition_en": null,
    "source": "fimea_en_fi_terminology",
    "source_page_fi": 106,
    "official_ich_glossary_entry": false
  },
  {
    "id": "ich-e6-r3-term-005",
    "entry_type": "translation_mapping",
    "term_en": "adverse drug reaction",
    "preferred_label_fi": "lääkkeen haittavaikutus",
    "definition_fi": null,
    "definition_en": null,
    "source": "fimea_en_fi_terminology",
    "source_page_fi": 106,
    "official_ich_glossary_entry": false
  },
  {
    "id": "ich-e6-r3-term-006",
    "entry_type": "translation_mapping",
    "term_en": "adverse drug reaction patterns",
    "preferred_label_fi": "lääkkeen haittavaikutusten esiintymismallit",
    "definition_fi": null,
    "definition_en": null,
    "source": "fimea_en_fi_terminology",
    "source_page_fi": 106,
    "official_ich_glossary_entry": false
  },
  {
    "id": "ich-e6-r3-term-007",
    "entry_type": "translation_mapping",
    "term_en": "adverse event",
    "preferred_label_fi": "haittatapahtuma",
    "definition_fi": null,
    "definition_en": null,
    "source": "fimea_en_fi_terminology",
    "source_page_fi": 106,
    "official_ich_glossary_entry": false
  },
  {
    "id": "ich-e6-r3-term-008",
    "entry_type": "translation_mapping",
    "term_en": "adverse reaction",
    "preferred_label_fi": "haittavaikutus",
    "definition_fi": null,
    "definition_en": null,
    "source": "fimea_en_fi_terminology",
    "source_page_fi": 106,
    "official_ich_glossary_entry": false
  },
  {
    "id": "ich-e6-r3-term-009",
    "entry_type": "translation_mapping",
    "term_en": "aggregate",
    "preferred_label_fi": "koota yhteen",
    "definition_fi": null,
    "definition_en": null,
    "source": "fimea_en_fi_terminology",
    "source_page_fi": 106,
    "official_ich_glossary_entry": false
  },
  {
    "id": "ich-e6-r3-term-010",
    "entry_type": "translation_mapping",
    "term_en": "analysis sets decisions",
    "preferred_label_fi": "analyysijoukkojen valintapäätökset",
    "definition_fi": null,
    "definition_en": null,
    "source": "fimea_en_fi_terminology",
    "source_page_fi": 106,
    "official_ich_glossary_entry": false
  },
  {
    "id": "ich-e6-r3-term-011",
    "entry_type": "translation_mapping",
    "term_en": "annex",
    "preferred_label_fi": "liite",
    "definition_fi": null,
    "definition_en": null,
    "source": "fimea_en_fi_terminology",
    "source_page_fi": 106,
    "official_ich_glossary_entry": false
  },
  {
    "id": "ich-e6-r3-term-012",
    "entry_type": "translation_mapping",
    "term_en": "appendix",
    "preferred_label_fi": "täydentävä liite",
    "definition_fi": null,
    "definition_en": null,
    "source": "fimea_en_fi_terminology",
    "source_page_fi": 106,
    "official_ich_glossary_entry": false
  },
  {
    "id": "ich-e6-r3-term-013",
    "entry_type": "translation_mapping",
    "term_en": "appropriate decision making",
    "preferred_label_fi": "asianmukainen päätöksenteko",
    "definition_fi": null,
    "definition_en": null,
    "source": "fimea_en_fi_terminology",
    "source_page_fi": 106,
    "official_ich_glossary_entry": false
  },
  {
    "id": "ich-e6-r3-term-014",
    "entry_type": "translation_mapping",
    "term_en": "assent",
    "preferred_label_fi": "alaikäisen suostumus",
    "definition_fi": null,
    "definition_en": null,
    "source": "fimea_en_fi_terminology",
    "source_page_fi": 106,
    "official_ich_glossary_entry": false
  },
  {
    "id": "ich-e6-r3-term-015",
    "entry_type": "translation_mapping",
    "term_en": "assessment of efficacy",
    "preferred_label_fi": "tehokkuuden arviointi",
    "definition_fi": null,
    "definition_en": null,
    "source": "fimea_en_fi_terminology",
    "source_page_fi": 106,
    "official_ich_glossary_entry": false
  },
  {
    "id": "ich-e6-r3-term-016",
    "entry_type": "translation_mapping",
    "term_en": "assessment of safety",
    "preferred_label_fi": "turvallisuuden arviointi",
    "definition_fi": null,
    "definition_en": null,
    "source": "fimea_en_fi_terminology",
    "source_page_fi": 106,
    "official_ich_glossary_entry": false
  },
  {
    "id": "ich-e6-r3-term-017",
    "entry_type": "translation_mapping",
    "term_en": "audit",
    "preferred_label_fi": "auditointi",
    "definition_fi": null,
    "definition_en": null,
    "source": "fimea_en_fi_terminology",
    "source_page_fi": 106,
    "official_ich_glossary_entry": false
  },
  {
    "id": "ich-e6-r3-term-018",
    "entry_type": "translation_mapping",
    "term_en": "audit certificate",
    "preferred_label_fi": "auditointitodistus",
    "definition_fi": null,
    "definition_en": null,
    "source": "fimea_en_fi_terminology",
    "source_page_fi": 106,
    "official_ich_glossary_entry": false
  },
  {
    "id": "ich-e6-r3-term-019",
    "entry_type": "translation_mapping",
    "term_en": "audit frequency",
    "preferred_label_fi": "auditointiväli (kuinka usein auditoidaan)",
    "definition_fi": null,
    "definition_en": null,
    "source": "fimea_en_fi_terminology",
    "source_page_fi": 106,
    "official_ich_glossary_entry": false
  },
  {
    "id": "ich-e6-r3-term-020",
    "entry_type": "translation_mapping",
    "term_en": "audit report",
    "preferred_label_fi": "auditointiraportti",
    "definition_fi": null,
    "definition_en": null,
    "source": "fimea_en_fi_terminology",
    "source_page_fi": 106,
    "official_ich_glossary_entry": false
  },
  {
    "id": "ich-e6-r3-term-021",
    "entry_type": "translation_mapping",
    "term_en": "audit trail",
    "preferred_label_fi": "jäljitettävyysketju",
    "definition_fi": null,
    "definition_en": null,
    "source": "fimea_en_fi_terminology",
    "source_page_fi": 106,
    "official_ich_glossary_entry": false
  },
  {
    "id": "ich-e6-r3-term-022",
    "entry_type": "translation_mapping",
    "term_en": "basic product information brochure",
    "preferred_label_fi": "valmisteyhteenveto (tai muut olemassa olevat hyväksytyt tuotetiedot)",
    "definition_fi": null,
    "definition_en": null,
    "source": "fimea_en_fi_terminology",
    "source_page_fi": 106,
    "official_ich_glossary_entry": false
  },
  {
    "id": "ich-e6-r3-term-023",
    "entry_type": "translation_mapping",
    "term_en": "bias",
    "preferred_label_fi": "harha",
    "definition_fi": null,
    "definition_en": null,
    "source": "fimea_en_fi_terminology",
    "source_page_fi": 106,
    "official_ich_glossary_entry": false
  },
  {
    "id": "ich-e6-r3-term-024",
    "entry_type": "translation_mapping",
    "term_en": "bioavailability",
    "preferred_label_fi": "biologinen hyötyosuus",
    "definition_fi": null,
    "definition_en": null,
    "source": "fimea_en_fi_terminology",
    "source_page_fi": 106,
    "official_ich_glossary_entry": false
  },
  {
    "id": "ich-e6-r3-term-025",
    "entry_type": "translation_mapping",
    "term_en": "biostatistician",
    "preferred_label_fi": "biostatistikko",
    "definition_fi": null,
    "definition_en": null,
    "source": "fimea_en_fi_terminology",
    "source_page_fi": 106,
    "official_ich_glossary_entry": false
  },
  {
    "id": "ich-e6-r3-term-026",
    "entry_type": "translation_mapping",
    "term_en": "blinding / masking",
    "preferred_label_fi": "sokkoutus",
    "definition_fi": null,
    "definition_en": null,
    "source": "fimea_en_fi_terminology",
    "source_page_fi": 106,
    "official_ich_glossary_entry": false
  },
  {
    "id": "ich-e6-r3-term-027",
    "entry_type": "translation_mapping",
    "term_en": "case report form",
    "preferred_label_fi": "tietojenkeruulomake",
    "definition_fi": null,
    "definition_en": null,
    "source": "fimea_en_fi_terminology",
    "source_page_fi": 106,
    "official_ich_glossary_entry": false
  },
  {
    "id": "ich-e6-r3-term-028",
    "entry_type": "translation_mapping",
    "term_en": "central image reading facility",
    "preferred_label_fi": "keskitetty kuvantamisen tulkinnan yksikkö",
    "definition_fi": null,
    "definition_en": null,
    "source": "fimea_en_fi_terminology",
    "source_page_fi": 106,
    "official_ich_glossary_entry": false
  },
  {
    "id": "ich-e6-r3-term-029",
    "entry_type": "translation_mapping",
    "term_en": "centralised monitoring",
    "preferred_label_fi": "keskitetty monitorointi",
    "definition_fi": null,
    "definition_en": null,
    "source": "fimea_en_fi_terminology",
    "source_page_fi": 106,
    "official_ich_glossary_entry": false
  },
  {
    "id": "ich-e6-r3-term-030",
    "entry_type": "translation_mapping",
    "term_en": "certified copy",
    "preferred_label_fi": "varmennettu kopio",
    "definition_fi": null,
    "definition_en": null,
    "source": "fimea_en_fi_terminology",
    "source_page_fi": 106,
    "official_ich_glossary_entry": false
  },
  {
    "id": "ich-e6-r3-term-031",
    "entry_type": "translation_mapping",
    "term_en": "clinical development",
    "preferred_label_fi": "kliininen kehitys",
    "definition_fi": null,
    "definition_en": null,
    "source": "fimea_en_fi_terminology",
    "source_page_fi": 106,
    "official_ich_glossary_entry": false
  },
  {
    "id": "ich-e6-r3-term-032",
    "entry_type": "translation_mapping",
    "term_en": "clinical management",
    "preferred_label_fi": "kliininen hoito",
    "definition_fi": null,
    "definition_en": null,
    "source": "fimea_en_fi_terminology",
    "source_page_fi": 106,
    "official_ich_glossary_entry": false
  },
  {
    "id": "ich-e6-r3-term-033",
    "entry_type": "translation_mapping",
    "term_en": "clinical research",
    "preferred_label_fi": "kliininen tutkimus",
    "definition_fi": null,
    "definition_en": null,
    "source": "fimea_en_fi_terminology",
    "source_page_fi": 106,
    "official_ich_glossary_entry": false
  },
  {
    "id": "ich-e6-r3-term-034",
    "entry_type": "translation_mapping",
    "term_en": "clinical trial",
    "preferred_label_fi": "kliininen lääketutkimus",
    "definition_fi": null,
    "definition_en": null,
    "source": "fimea_en_fi_terminology",
    "source_page_fi": 106,
    "official_ich_glossary_entry": false
  },
  {
    "id": "ich-e6-r3-term-035",
    "entry_type": "translation_mapping",
    "term_en": "clinical trial protocol",
    "preferred_label_fi": "(kliinisen lääketutkimuksen) tutkimussuunnitelma",
    "definition_fi": null,
    "definition_en": null,
    "source": "fimea_en_fi_terminology",
    "source_page_fi": 106,
    "official_ich_glossary_entry": false
  },
  {
    "id": "ich-e6-r3-term-036",
    "entry_type": "translation_mapping",
    "term_en": "clinical trial/study report (CSR)",
    "preferred_label_fi": "kliinisen lääketutkimuksen raportti (CSR)",
    "definition_fi": null,
    "definition_en": null,
    "source": "fimea_en_fi_terminology",
    "source_page_fi": 106,
    "official_ich_glossary_entry": false
  },
  {
    "id": "ich-e6-r3-term-037",
    "entry_type": "translation_mapping",
    "term_en": "comparator",
    "preferred_label_fi": "vertailuvalmiste",
    "definition_fi": null,
    "definition_en": null,
    "source": "fimea_en_fi_terminology",
    "source_page_fi": 106,
    "official_ich_glossary_entry": false
  },
  {
    "id": "ich-e6-r3-term-038",
    "entry_type": "translation_mapping",
    "term_en": "compliance",
    "preferred_label_fi": "vaatimustenmukaisuus",
    "definition_fi": null,
    "definition_en": null,
    "source": "fimea_en_fi_terminology",
    "source_page_fi": 106,
    "official_ich_glossary_entry": false
  },
  {
    "id": "ich-e6-r3-term-039",
    "entry_type": "translation_mapping",
    "term_en": "compound",
    "preferred_label_fi": "yhdiste",
    "definition_fi": null,
    "definition_en": null,
    "source": "fimea_en_fi_terminology",
    "source_page_fi": 107,
    "official_ich_glossary_entry": false
  },
  {
    "id": "ich-e6-r3-term-040",
    "entry_type": "translation_mapping",
    "term_en": "computerized system",
    "preferred_label_fi": "tietokoneistettu järjestelmä",
    "definition_fi": null,
    "definition_en": null,
    "source": "fimea_en_fi_terminology",
    "source_page_fi": 107,
    "official_ich_glossary_entry": false
  },
  {
    "id": "ich-e6-r3-term-041",
    "entry_type": "translation_mapping",
    "term_en": "computerized system validation",
    "preferred_label_fi": "tietokoneistettujen järjestelmien validointi",
    "definition_fi": null,
    "definition_en": null,
    "source": "fimea_en_fi_terminology",
    "source_page_fi": 107,
    "official_ich_glossary_entry": false
  },
  {
    "id": "ich-e6-r3-term-042",
    "entry_type": "translation_mapping",
    "term_en": "contract research organization (CRO)",
    "preferred_label_fi": "sopimustutkimusorganisaatio (CRO)",
    "definition_fi": null,
    "definition_en": null,
    "source": "fimea_en_fi_terminology",
    "source_page_fi": 107,
    "official_ich_glossary_entry": false
  },
  {
    "id": "ich-e6-r3-term-043",
    "entry_type": "translation_mapping",
    "term_en": "coordinating investigator",
    "preferred_label_fi": "koordinoiva tutkija",
    "definition_fi": null,
    "definition_en": null,
    "source": "fimea_en_fi_terminology",
    "source_page_fi": 107,
    "official_ich_glossary_entry": false
  },
  {
    "id": "ich-e6-r3-term-044",
    "entry_type": "translation_mapping",
    "term_en": "criticality (higher criticality)",
    "preferred_label_fi": "kriittisyys (kriittisempi)",
    "definition_fi": null,
    "definition_en": null,
    "source": "fimea_en_fi_terminology",
    "source_page_fi": 107,
    "official_ich_glossary_entry": false
  },
  {
    "id": "ich-e6-r3-term-045",
    "entry_type": "translation_mapping",
    "term_en": "critical to quality factor",
    "preferred_label_fi": "kriittinen laatutekijä",
    "definition_fi": null,
    "definition_en": null,
    "source": "fimea_en_fi_terminology",
    "source_page_fi": 107,
    "official_ich_glossary_entry": false
  },
  {
    "id": "ich-e6-r3-term-046",
    "entry_type": "translation_mapping",
    "term_en": "data acquisition tool",
    "preferred_label_fi": "tiedonkeruutyökalu",
    "definition_fi": null,
    "definition_en": null,
    "source": "fimea_en_fi_terminology",
    "source_page_fi": 107,
    "official_ich_glossary_entry": false
  },
  {
    "id": "ich-e6-r3-term-047",
    "entry_type": "translation_mapping",
    "term_en": "data analytics",
    "preferred_label_fi": "data-analytiikka",
    "definition_fi": null,
    "definition_en": null,
    "source": "fimea_en_fi_terminology",
    "source_page_fi": 107,
    "official_ich_glossary_entry": false
  },
  {
    "id": "ich-e6-r3-term-048",
    "entry_type": "translation_mapping",
    "term_en": "database lock checklist",
    "preferred_label_fi": "tietokannan lukituksen tarkistuslista",
    "definition_fi": null,
    "definition_en": null,
    "source": "fimea_en_fi_terminology",
    "source_page_fi": 107,
    "official_ich_glossary_entry": false
  },
  {
    "id": "ich-e6-r3-term-049",
    "entry_type": "translation_mapping",
    "term_en": "data handling",
    "preferred_label_fi": "tietojen käsittely",
    "definition_fi": null,
    "definition_en": null,
    "source": "fimea_en_fi_terminology",
    "source_page_fi": 107,
    "official_ich_glossary_entry": false
  },
  {
    "id": "ich-e6-r3-term-050",
    "entry_type": "translation_mapping",
    "term_en": "data integrity",
    "preferred_label_fi": "tietojen eheys",
    "definition_fi": null,
    "definition_en": null,
    "source": "fimea_en_fi_terminology",
    "source_page_fi": 107,
    "official_ich_glossary_entry": false
  },
  {
    "id": "ich-e6-r3-term-051",
    "entry_type": "translation_mapping",
    "term_en": "data management",
    "preferred_label_fi": "tiedonhallinta",
    "definition_fi": null,
    "definition_en": null,
    "source": "fimea_en_fi_terminology",
    "source_page_fi": 107,
    "official_ich_glossary_entry": false
  },
  {
    "id": "ich-e6-r3-term-052",
    "entry_type": "translation_mapping",
    "term_en": "data management plan",
    "preferred_label_fi": "tiedonhallintasuunnitelma",
    "definition_fi": null,
    "definition_en": null,
    "source": "fimea_en_fi_terminology",
    "source_page_fi": 107,
    "official_ich_glossary_entry": false
  },
  {
    "id": "ich-e6-r3-term-053",
    "entry_type": "translation_mapping",
    "term_en": "data manager",
    "preferred_label_fi": "tiedonhallinnan asiantuntija (data manager)",
    "definition_fi": null,
    "definition_en": null,
    "source": "fimea_en_fi_terminology",
    "source_page_fi": 107,
    "official_ich_glossary_entry": false
  },
  {
    "id": "ich-e6-r3-term-054",
    "entry_type": "translation_mapping",
    "term_en": "data outlier",
    "preferred_label_fi": "oudokki",
    "definition_fi": null,
    "definition_en": null,
    "source": "fimea_en_fi_terminology",
    "source_page_fi": 107,
    "official_ich_glossary_entry": false
  },
  {
    "id": "ich-e6-r3-term-055",
    "entry_type": "translation_mapping",
    "term_en": "data scientist",
    "preferred_label_fi": "data-analyytikko",
    "definition_fi": null,
    "definition_en": null,
    "source": "fimea_en_fi_terminology",
    "source_page_fi": 107,
    "official_ich_glossary_entry": false
  },
  {
    "id": "ich-e6-r3-term-056",
    "entry_type": "translation_mapping",
    "term_en": "data set",
    "preferred_label_fi": "tietoaineisto / datajoukko",
    "definition_fi": null,
    "definition_en": null,
    "source": "fimea_en_fi_terminology",
    "source_page_fi": 107,
    "official_ich_glossary_entry": false
  },
  {
    "id": "ich-e6-r3-term-057",
    "entry_type": "translation_mapping",
    "term_en": "decentralised elements",
    "preferred_label_fi": "hajautetut elementit",
    "definition_fi": null,
    "definition_en": null,
    "source": "fimea_en_fi_terminology",
    "source_page_fi": 107,
    "official_ich_glossary_entry": false
  },
  {
    "id": "ich-e6-r3-term-058",
    "entry_type": "translation_mapping",
    "term_en": "decentralised settings",
    "preferred_label_fi": "hajautetut toimintaympäristöt",
    "definition_fi": null,
    "definition_en": null,
    "source": "fimea_en_fi_terminology",
    "source_page_fi": 107,
    "official_ich_glossary_entry": false
  },
  {
    "id": "ich-e6-r3-term-059",
    "entry_type": "translation_mapping",
    "term_en": "decoding, emergency decoding",
    "preferred_label_fi": "koodin purku, koodin purku hätätilanteissa",
    "definition_fi": null,
    "definition_en": null,
    "source": "fimea_en_fi_terminology",
    "source_page_fi": 107,
    "official_ich_glossary_entry": false
  },
  {
    "id": "ich-e6-r3-term-060",
    "entry_type": "translation_mapping",
    "term_en": "direct access",
    "preferred_label_fi": "suora pääsy",
    "definition_fi": null,
    "definition_en": null,
    "source": "fimea_en_fi_terminology",
    "source_page_fi": 107,
    "official_ich_glossary_entry": false
  },
  {
    "id": "ich-e6-r3-term-061",
    "entry_type": "translation_mapping",
    "term_en": "dose",
    "preferred_label_fi": "annos",
    "definition_fi": null,
    "definition_en": null,
    "source": "fimea_en_fi_terminology",
    "source_page_fi": 107,
    "official_ich_glossary_entry": false
  },
  {
    "id": "ich-e6-r3-term-062",
    "entry_type": "translation_mapping",
    "term_en": "dose interval",
    "preferred_label_fi": "annosväli",
    "definition_fi": null,
    "definition_en": null,
    "source": "fimea_en_fi_terminology",
    "source_page_fi": 107,
    "official_ich_glossary_entry": false
  },
  {
    "id": "ich-e6-r3-term-063",
    "entry_type": "translation_mapping",
    "term_en": "drug",
    "preferred_label_fi": "lääke",
    "definition_fi": null,
    "definition_en": null,
    "source": "fimea_en_fi_terminology",
    "source_page_fi": 107,
    "official_ich_glossary_entry": false
  },
  {
    "id": "ich-e6-r3-term-064",
    "entry_type": "translation_mapping",
    "term_en": "duration of dosing",
    "preferred_label_fi": "annostelun kesto",
    "definition_fi": null,
    "definition_en": null,
    "source": "fimea_en_fi_terminology",
    "source_page_fi": 107,
    "official_ich_glossary_entry": false
  },
  {
    "id": "ich-e6-r3-term-065",
    "entry_type": "translation_mapping",
    "term_en": "efficacy endpoint",
    "preferred_label_fi": "tehoon liittyvä päätetapahtuma",
    "definition_fi": null,
    "definition_en": null,
    "source": "fimea_en_fi_terminology",
    "source_page_fi": 107,
    "official_ich_glossary_entry": false
  },
  {
    "id": "ich-e6-r3-term-066",
    "entry_type": "translation_mapping",
    "term_en": "electronic health records",
    "preferred_label_fi": "sähköiset potilasasiakirjat (asiakastiedot)",
    "definition_fi": null,
    "definition_en": null,
    "source": "fimea_en_fi_terminology",
    "source_page_fi": 107,
    "official_ich_glossary_entry": false
  },
  {
    "id": "ich-e6-r3-term-067",
    "entry_type": "translation_mapping",
    "term_en": "eligible trial participant",
    "preferred_label_fi": "tutkimukseen soveltuva osallistuja",
    "definition_fi": null,
    "definition_en": null,
    "source": "fimea_en_fi_terminology",
    "source_page_fi": 107,
    "official_ich_glossary_entry": false
  },
  {
    "id": "ich-e6-r3-term-068",
    "entry_type": "translation_mapping",
    "term_en": "elimination",
    "preferred_label_fi": "eliminaatio",
    "definition_fi": null,
    "definition_en": null,
    "source": "fimea_en_fi_terminology",
    "source_page_fi": 107,
    "official_ich_glossary_entry": false
  },
  {
    "id": "ich-e6-r3-term-069",
    "entry_type": "translation_mapping",
    "term_en": "endpoint assessment",
    "preferred_label_fi": "päätetapahtuman arviointi",
    "definition_fi": null,
    "definition_en": null,
    "source": "fimea_en_fi_terminology",
    "source_page_fi": 107,
    "official_ich_glossary_entry": false
  },
  {
    "id": "ich-e6-r3-term-070",
    "entry_type": "translation_mapping",
    "term_en": "enrolment log",
    "preferred_label_fi": "lista tutkimukseen otetuista osallistujista",
    "definition_fi": null,
    "definition_en": null,
    "source": "fimea_en_fi_terminology",
    "source_page_fi": 107,
    "official_ich_glossary_entry": false
  },
  {
    "id": "ich-e6-r3-term-071",
    "entry_type": "translation_mapping",
    "term_en": "ePRO",
    "preferred_label_fi": "potilaan sähköisesti raportoima(t) tulos/tulokset (ePRO)",
    "definition_fi": null,
    "definition_en": null,
    "source": "fimea_en_fi_terminology",
    "source_page_fi": 107,
    "official_ich_glossary_entry": false
  },
  {
    "id": "ich-e6-r3-term-072",
    "entry_type": "translation_mapping",
    "term_en": "escalation",
    "preferred_label_fi": "eskalointi",
    "definition_fi": null,
    "definition_en": null,
    "source": "fimea_en_fi_terminology",
    "source_page_fi": 107,
    "official_ich_glossary_entry": false
  },
  {
    "id": "ich-e6-r3-term-073",
    "entry_type": "translation_mapping",
    "term_en": "essential records",
    "preferred_label_fi": "oleelliset tallenteet",
    "definition_fi": null,
    "definition_en": null,
    "source": "fimea_en_fi_terminology",
    "source_page_fi": 107,
    "official_ich_glossary_entry": false
  },
  {
    "id": "ich-e6-r3-term-074",
    "entry_type": "translation_mapping",
    "term_en": "estimand",
    "preferred_label_fi": "estimandi",
    "definition_fi": null,
    "definition_en": null,
    "source": "fimea_en_fi_terminology",
    "source_page_fi": 107,
    "official_ich_glossary_entry": false
  },
  {
    "id": "ich-e6-r3-term-075",
    "entry_type": "translation_mapping",
    "term_en": "expectedness",
    "preferred_label_fi": "odotettavuus",
    "definition_fi": null,
    "definition_en": null,
    "source": "fimea_en_fi_terminology",
    "source_page_fi": 107,
    "official_ich_glossary_entry": false
  },
  {
    "id": "ich-e6-r3-term-076",
    "entry_type": "translation_mapping",
    "term_en": "expedited reporting",
    "preferred_label_fi": "nopeutettu raportointi",
    "definition_fi": null,
    "definition_en": null,
    "source": "fimea_en_fi_terminology",
    "source_page_fi": 107,
    "official_ich_glossary_entry": false
  },
  {
    "id": "ich-e6-r3-term-077",
    "entry_type": "translation_mapping",
    "term_en": "favourable opinion",
    "preferred_label_fi": "puoltava lausunto",
    "definition_fi": null,
    "definition_en": null,
    "source": "fimea_en_fi_terminology",
    "source_page_fi": 107,
    "official_ich_glossary_entry": false
  },
  {
    "id": "ich-e6-r3-term-078",
    "entry_type": "translation_mapping",
    "term_en": "fitness for purpose",
    "preferred_label_fi": "tarkoitukseen sopivuus",
    "definition_fi": null,
    "definition_en": null,
    "source": "fimea_en_fi_terminology",
    "source_page_fi": 107,
    "official_ich_glossary_entry": false
  },
  {
    "id": "ich-e6-r3-term-079",
    "entry_type": "translation_mapping",
    "term_en": "formulation",
    "preferred_label_fi": "formulaatio",
    "definition_fi": null,
    "definition_en": null,
    "source": "fimea_en_fi_terminology",
    "source_page_fi": 108,
    "official_ich_glossary_entry": false
  },
  {
    "id": "ich-e6-r3-term-080",
    "entry_type": "translation_mapping",
    "term_en": "frequency",
    "preferred_label_fi": "esiintymistiheys",
    "definition_fi": null,
    "definition_en": null,
    "source": "fimea_en_fi_terminology",
    "source_page_fi": 108,
    "official_ich_glossary_entry": false
  },
  {
    "id": "ich-e6-r3-term-081",
    "entry_type": "translation_mapping",
    "term_en": "genotoxicity",
    "preferred_label_fi": "genotoksisuus",
    "definition_fi": null,
    "definition_en": null,
    "source": "fimea_en_fi_terminology",
    "source_page_fi": 108,
    "official_ich_glossary_entry": false
  },
  {
    "id": "ich-e6-r3-term-082",
    "entry_type": "translation_mapping",
    "term_en": "good clinical practise (GCP)",
    "preferred_label_fi": "hyvä kliininen tutkimustapa (GCP)",
    "definition_fi": null,
    "definition_en": null,
    "source": "fimea_en_fi_terminology",
    "source_page_fi": 108,
    "official_ich_glossary_entry": false
  },
  {
    "id": "ich-e6-r3-term-083",
    "entry_type": "translation_mapping",
    "term_en": "human equivalent dose",
    "preferred_label_fi": "vastaava ihmisannos",
    "definition_fi": null,
    "definition_en": null,
    "source": "fimea_en_fi_terminology",
    "source_page_fi": 108,
    "official_ich_glossary_entry": false
  },
  {
    "id": "ich-e6-r3-term-084",
    "entry_type": "translation_mapping",
    "term_en": "Identification code",
    "preferred_label_fi": "tunnistekoodi",
    "definition_fi": null,
    "definition_en": null,
    "source": "fimea_en_fi_terminology",
    "source_page_fi": 108,
    "official_ich_glossary_entry": false
  },
  {
    "id": "ich-e6-r3-term-085",
    "entry_type": "translation_mapping",
    "term_en": "impaired organ function",
    "preferred_label_fi": "elimen toimintahäiriö",
    "definition_fi": null,
    "definition_en": null,
    "source": "fimea_en_fi_terminology",
    "source_page_fi": 108,
    "official_ich_glossary_entry": false
  },
  {
    "id": "ich-e6-r3-term-086",
    "entry_type": "translation_mapping",
    "term_en": "Impartial witness",
    "preferred_label_fi": "puolueeton todistaja",
    "definition_fi": null,
    "definition_en": null,
    "source": "fimea_en_fi_terminology",
    "source_page_fi": 108,
    "official_ich_glossary_entry": false
  },
  {
    "id": "ich-e6-r3-term-087",
    "entry_type": "translation_mapping",
    "term_en": "implement",
    "preferred_label_fi": "toteuttaa, ottaa käyttöön, panna täytäntöön",
    "definition_fi": null,
    "definition_en": null,
    "source": "fimea_en_fi_terminology",
    "source_page_fi": 108,
    "official_ich_glossary_entry": false
  },
  {
    "id": "ich-e6-r3-term-088",
    "entry_type": "translation_mapping",
    "term_en": "Important protocol deviation",
    "preferred_label_fi": "merkittävä poikkeama tutkimussuunnitelmasta",
    "definition_fi": null,
    "definition_en": null,
    "source": "fimea_en_fi_terminology",
    "source_page_fi": 108,
    "official_ich_glossary_entry": false
  },
  {
    "id": "ich-e6-r3-term-089",
    "entry_type": "translation_mapping",
    "term_en": "Incident",
    "preferred_label_fi": "tapahtuma",
    "definition_fi": null,
    "definition_en": null,
    "source": "fimea_en_fi_terminology",
    "source_page_fi": 108,
    "official_ich_glossary_entry": false
  },
  {
    "id": "ich-e6-r3-term-090",
    "entry_type": "translation_mapping",
    "term_en": "Independent Data Monitoring Committee (IDMC)",
    "preferred_label_fi": "riippumaton tietojenseurantatoimikunta (IDMC)",
    "definition_fi": null,
    "definition_en": null,
    "source": "fimea_en_fi_terminology",
    "source_page_fi": 108,
    "official_ich_glossary_entry": false
  },
  {
    "id": "ich-e6-r3-term-091",
    "entry_type": "translation_mapping",
    "term_en": "Independent Ethics Committee (IEC)",
    "preferred_label_fi": "riippumaton eettinen toimikunta",
    "definition_fi": null,
    "definition_en": null,
    "source": "fimea_en_fi_terminology",
    "source_page_fi": 108,
    "official_ich_glossary_entry": false
  },
  {
    "id": "ich-e6-r3-term-092",
    "entry_type": "translation_mapping",
    "term_en": "indication",
    "preferred_label_fi": "käyttöaihe",
    "definition_fi": null,
    "definition_en": null,
    "source": "fimea_en_fi_terminology",
    "source_page_fi": 108,
    "official_ich_glossary_entry": false
  },
  {
    "id": "ich-e6-r3-term-093",
    "entry_type": "translation_mapping",
    "term_en": "Informed consent",
    "preferred_label_fi": "tietoon perustuva suostumus",
    "definition_fi": null,
    "definition_en": null,
    "source": "fimea_en_fi_terminology",
    "source_page_fi": 108,
    "official_ich_glossary_entry": false
  },
  {
    "id": "ich-e6-r3-term-094",
    "entry_type": "translation_mapping",
    "term_en": "injury",
    "preferred_label_fi": "henkilövahinko, haitta",
    "definition_fi": null,
    "definition_en": null,
    "source": "fimea_en_fi_terminology",
    "source_page_fi": 108,
    "official_ich_glossary_entry": false
  },
  {
    "id": "ich-e6-r3-term-095",
    "entry_type": "translation_mapping",
    "term_en": "inspection",
    "preferred_label_fi": "(viranomais)tarkastus",
    "definition_fi": null,
    "definition_en": null,
    "source": "fimea_en_fi_terminology",
    "source_page_fi": 108,
    "official_ich_glossary_entry": false
  },
  {
    "id": "ich-e6-r3-term-096",
    "entry_type": "translation_mapping",
    "term_en": "institution",
    "preferred_label_fi": "tutkimuslaitos",
    "definition_fi": null,
    "definition_en": null,
    "source": "fimea_en_fi_terminology",
    "source_page_fi": 108,
    "official_ich_glossary_entry": false
  },
  {
    "id": "ich-e6-r3-term-097",
    "entry_type": "translation_mapping",
    "term_en": "Institutional Review Board (IRB)",
    "preferred_label_fi": "tutkimuslaitoksen arviointilautakunta",
    "definition_fi": null,
    "definition_en": null,
    "source": "fimea_en_fi_terminology",
    "source_page_fi": 108,
    "official_ich_glossary_entry": false
  },
  {
    "id": "ich-e6-r3-term-098",
    "entry_type": "translation_mapping",
    "term_en": "Interactive Response Technologies (IRT)",
    "preferred_label_fi": "vuorovaikutteiset vastausjärjestelmät (IRT)",
    "definition_fi": null,
    "definition_en": null,
    "source": "fimea_en_fi_terminology",
    "source_page_fi": 108,
    "official_ich_glossary_entry": false
  },
  {
    "id": "ich-e6-r3-term-099",
    "entry_type": "translation_mapping",
    "term_en": "interface",
    "preferred_label_fi": "rajapinta",
    "definition_fi": null,
    "definition_en": null,
    "source": "fimea_en_fi_terminology",
    "source_page_fi": 108,
    "official_ich_glossary_entry": false
  },
  {
    "id": "ich-e6-r3-term-100",
    "entry_type": "translation_mapping",
    "term_en": "Interim clinical trial/study report",
    "preferred_label_fi": "kliinisen lääketutkimuksen väliraportti",
    "definition_fi": null,
    "definition_en": null,
    "source": "fimea_en_fi_terminology",
    "source_page_fi": 108,
    "official_ich_glossary_entry": false
  },
  {
    "id": "ich-e6-r3-term-101",
    "entry_type": "translation_mapping",
    "term_en": "investigational product",
    "preferred_label_fi": "tutkimusvalmiste",
    "definition_fi": null,
    "definition_en": null,
    "source": "fimea_en_fi_terminology",
    "source_page_fi": 108,
    "official_ich_glossary_entry": false
  },
  {
    "id": "ich-e6-r3-term-102",
    "entry_type": "translation_mapping",
    "term_en": "investigator",
    "preferred_label_fi": "tutkija",
    "definition_fi": null,
    "definition_en": null,
    "source": "fimea_en_fi_terminology",
    "source_page_fi": 108,
    "official_ich_glossary_entry": false
  },
  {
    "id": "ich-e6-r3-term-103",
    "entry_type": "translation_mapping",
    "term_en": "investigator-initiated",
    "preferred_label_fi": "tutkijalähtöinen",
    "definition_fi": null,
    "definition_en": null,
    "source": "fimea_en_fi_terminology",
    "source_page_fi": 108,
    "official_ich_glossary_entry": false
  },
  {
    "id": "ich-e6-r3-term-104",
    "entry_type": "translation_mapping",
    "term_en": "investigator's brochure (IB)",
    "preferred_label_fi": "tutkijan tietopaketti (IB)",
    "definition_fi": null,
    "definition_en": null,
    "source": "fimea_en_fi_terminology",
    "source_page_fi": 108,
    "official_ich_glossary_entry": false
  },
  {
    "id": "ich-e6-r3-term-105",
    "entry_type": "translation_mapping",
    "term_en": "investigator site",
    "preferred_label_fi": "tutkimuspaikka",
    "definition_fi": null,
    "definition_en": null,
    "source": "fimea_en_fi_terminology",
    "source_page_fi": 108,
    "official_ich_glossary_entry": false
  },
  {
    "id": "ich-e6-r3-term-106",
    "entry_type": "translation_mapping",
    "term_en": "investigator site file",
    "preferred_label_fi": "tutkijan kantatiedosto",
    "definition_fi": null,
    "definition_en": null,
    "source": "fimea_en_fi_terminology",
    "source_page_fi": 108,
    "official_ich_glossary_entry": false
  },
  {
    "id": "ich-e6-r3-term-107",
    "entry_type": "translation_mapping",
    "term_en": "investigator site staff",
    "preferred_label_fi": "tutkimusta suorittava henkilö(stö)",
    "definition_fi": null,
    "definition_en": null,
    "source": "fimea_en_fi_terminology",
    "source_page_fi": 108,
    "official_ich_glossary_entry": false
  },
  {
    "id": "ich-e6-r3-term-108",
    "entry_type": "translation_mapping",
    "term_en": "intercurrent event",
    "preferred_label_fi": "Tutkimushoidon aloittamisen jälkeen ilmenevä tapahtuma, joka vaikuttaa kliinisen tutkimuskysymyksen kannalta olennaisiin mittauksiin, niiden tulkintaan tai olemassaoloon [ks. ICH E9(R1)]",
    "definition_fi": null,
    "definition_en": null,
    "source": "fimea_en_fi_terminology",
    "source_page_fi": 108,
    "official_ich_glossary_entry": false
  },
  {
    "id": "ich-e6-r3-term-109",
    "entry_type": "translation_mapping",
    "term_en": "interventional clinical trial",
    "preferred_label_fi": "interventiotutkimus",
    "definition_fi": null,
    "definition_en": null,
    "source": "fimea_en_fi_terminology",
    "source_page_fi": 108,
    "official_ich_glossary_entry": false
  },
  {
    "id": "ich-e6-r3-term-110",
    "entry_type": "translation_mapping",
    "term_en": "issue",
    "preferred_label_fi": "asia, poikkeama, ongelma",
    "definition_fi": null,
    "definition_en": null,
    "source": "fimea_en_fi_terminology",
    "source_page_fi": 108,
    "official_ich_glossary_entry": false
  },
  {
    "id": "ich-e6-r3-term-111",
    "entry_type": "translation_mapping",
    "term_en": "labelling",
    "preferred_label_fi": "pakkausmerkintä",
    "definition_fi": null,
    "definition_en": null,
    "source": "fimea_en_fi_terminology",
    "source_page_fi": 108,
    "official_ich_glossary_entry": false
  },
  {
    "id": "ich-e6-r3-term-112",
    "entry_type": "translation_mapping",
    "term_en": "legally acceptable representative",
    "preferred_label_fi": "laillinen edustaja",
    "definition_fi": null,
    "definition_en": null,
    "source": "fimea_en_fi_terminology",
    "source_page_fi": 108,
    "official_ich_glossary_entry": false
  },
  {
    "id": "ich-e6-r3-term-113",
    "entry_type": "translation_mapping",
    "term_en": "line listings",
    "preferred_label_fi": "(rivikohtainen) listaus",
    "definition_fi": null,
    "definition_en": null,
    "source": "fimea_en_fi_terminology",
    "source_page_fi": 108,
    "official_ich_glossary_entry": false
  },
  {
    "id": "ich-e6-r3-term-114",
    "entry_type": "translation_mapping",
    "term_en": "malpractice",
    "preferred_label_fi": "hoitovirhe, virheellinen menettely",
    "definition_fi": null,
    "definition_en": null,
    "source": "fimea_en_fi_terminology",
    "source_page_fi": 109,
    "official_ich_glossary_entry": false
  },
  {
    "id": "ich-e6-r3-term-115",
    "entry_type": "translation_mapping",
    "term_en": "medicine",
    "preferred_label_fi": "lääke",
    "definition_fi": null,
    "definition_en": null,
    "source": "fimea_en_fi_terminology",
    "source_page_fi": 109,
    "official_ich_glossary_entry": false
  },
  {
    "id": "ich-e6-r3-term-116",
    "entry_type": "translation_mapping",
    "term_en": "metadata",
    "preferred_label_fi": "metatieto, metatiedot",
    "definition_fi": null,
    "definition_en": null,
    "source": "fimea_en_fi_terminology",
    "source_page_fi": 109,
    "official_ich_glossary_entry": false
  },
  {
    "id": "ich-e6-r3-term-117",
    "entry_type": "translation_mapping",
    "term_en": "monitor",
    "preferred_label_fi": "monitoroija",
    "definition_fi": null,
    "definition_en": null,
    "source": "fimea_en_fi_terminology",
    "source_page_fi": 109,
    "official_ich_glossary_entry": false
  },
  {
    "id": "ich-e6-r3-term-118",
    "entry_type": "translation_mapping",
    "term_en": "monitoring",
    "preferred_label_fi": "monitorointi",
    "definition_fi": null,
    "definition_en": null,
    "source": "fimea_en_fi_terminology",
    "source_page_fi": 109,
    "official_ich_glossary_entry": false
  },
  {
    "id": "ich-e6-r3-term-119",
    "entry_type": "translation_mapping",
    "term_en": "monitoring plan",
    "preferred_label_fi": "monitorointisuunnitelma",
    "definition_fi": null,
    "definition_en": null,
    "source": "fimea_en_fi_terminology",
    "source_page_fi": 109,
    "official_ich_glossary_entry": false
  },
  {
    "id": "ich-e6-r3-term-120",
    "entry_type": "translation_mapping",
    "term_en": "monitoring report",
    "preferred_label_fi": "monitorointiraportti",
    "definition_fi": null,
    "definition_en": null,
    "source": "fimea_en_fi_terminology",
    "source_page_fi": 109,
    "official_ich_glossary_entry": false
  },
  {
    "id": "ich-e6-r3-term-121",
    "entry_type": "translation_mapping",
    "term_en": "multicentre trial",
    "preferred_label_fi": "monikeskustutkimus",
    "definition_fi": null,
    "definition_en": null,
    "source": "fimea_en_fi_terminology",
    "source_page_fi": 109,
    "official_ich_glossary_entry": false
  },
  {
    "id": "ich-e6-r3-term-122",
    "entry_type": "translation_mapping",
    "term_en": "nonclinical pharmacology",
    "preferred_label_fi": "ei-kliininen farmakologia",
    "definition_fi": null,
    "definition_en": null,
    "source": "fimea_en_fi_terminology",
    "source_page_fi": 109,
    "official_ich_glossary_entry": false
  },
  {
    "id": "ich-e6-r3-term-123",
    "entry_type": "translation_mapping",
    "term_en": "nonclinical study",
    "preferred_label_fi": "ei-kliininen tutkimus",
    "definition_fi": null,
    "definition_en": null,
    "source": "fimea_en_fi_terminology",
    "source_page_fi": 109,
    "official_ich_glossary_entry": false
  },
  {
    "id": "ich-e6-r3-term-124",
    "entry_type": "translation_mapping",
    "term_en": "noncompliance",
    "preferred_label_fi": "vaatimusten laiminlyönti",
    "definition_fi": null,
    "definition_en": null,
    "source": "fimea_en_fi_terminology",
    "source_page_fi": 109,
    "official_ich_glossary_entry": false
  },
  {
    "id": "ich-e6-r3-term-125",
    "entry_type": "translation_mapping",
    "term_en": "oversight measures, oversight processes",
    "preferred_label_fi": "valvontamenettelyt, valvontatoimet",
    "definition_fi": null,
    "definition_en": null,
    "source": "fimea_en_fi_terminology",
    "source_page_fi": 109,
    "official_ich_glossary_entry": false
  },
  {
    "id": "ich-e6-r3-term-126",
    "entry_type": "translation_mapping",
    "term_en": "participant",
    "preferred_label_fi": "(tutkimukseen) osallistuja",
    "definition_fi": null,
    "definition_en": null,
    "source": "fimea_en_fi_terminology",
    "source_page_fi": 109,
    "official_ich_glossary_entry": false
  },
  {
    "id": "ich-e6-r3-term-127",
    "entry_type": "translation_mapping",
    "term_en": "penetration testing",
    "preferred_label_fi": "tunkeutumistestaus",
    "definition_fi": null,
    "definition_en": null,
    "source": "fimea_en_fi_terminology",
    "source_page_fi": 109,
    "official_ich_glossary_entry": false
  },
  {
    "id": "ich-e6-r3-term-128",
    "entry_type": "translation_mapping",
    "term_en": "performance metrics",
    "preferred_label_fi": "toiminnan tunnusluvut, suorituskykymittarit",
    "definition_fi": null,
    "definition_en": null,
    "source": "fimea_en_fi_terminology",
    "source_page_fi": 109,
    "official_ich_glossary_entry": false
  },
  {
    "id": "ich-e6-r3-term-129",
    "entry_type": "translation_mapping",
    "term_en": "pharmacological class",
    "preferred_label_fi": "farmakologinen luokka",
    "definition_fi": null,
    "definition_en": null,
    "source": "fimea_en_fi_terminology",
    "source_page_fi": 109,
    "official_ich_glossary_entry": false
  },
  {
    "id": "ich-e6-r3-term-130",
    "entry_type": "translation_mapping",
    "term_en": "placebo",
    "preferred_label_fi": "lumelääke, plasebo",
    "definition_fi": null,
    "definition_en": null,
    "source": "fimea_en_fi_terminology",
    "source_page_fi": 109,
    "official_ich_glossary_entry": false
  },
  {
    "id": "ich-e6-r3-term-131",
    "entry_type": "translation_mapping",
    "term_en": "principal investigator",
    "preferred_label_fi": "johtava tutkija, päätutkija",
    "definition_fi": null,
    "definition_en": null,
    "source": "fimea_en_fi_terminology",
    "source_page_fi": 109,
    "official_ich_glossary_entry": false
  },
  {
    "id": "ich-e6-r3-term-132",
    "entry_type": "translation_mapping",
    "term_en": "product",
    "preferred_label_fi": "valmiste",
    "definition_fi": null,
    "definition_en": null,
    "source": "fimea_en_fi_terminology",
    "source_page_fi": 109,
    "official_ich_glossary_entry": false
  },
  {
    "id": "ich-e6-r3-term-133",
    "entry_type": "translation_mapping",
    "term_en": "product specifications",
    "preferred_label_fi": "valmisteyhteenveto",
    "definition_fi": null,
    "definition_en": null,
    "source": "fimea_en_fi_terminology",
    "source_page_fi": 109,
    "official_ich_glossary_entry": false
  },
  {
    "id": "ich-e6-r3-term-134",
    "entry_type": "translation_mapping",
    "term_en": "proportionate risk-based approach",
    "preferred_label_fi": "oikeasuhtainen riskiperusteinen lähestymistapa",
    "definition_fi": null,
    "definition_en": null,
    "source": "fimea_en_fi_terminology",
    "source_page_fi": 109,
    "official_ich_glossary_entry": false
  },
  {
    "id": "ich-e6-r3-term-135",
    "entry_type": "translation_mapping",
    "term_en": "protocol",
    "preferred_label_fi": "tutkimussuunnitelma",
    "definition_fi": null,
    "definition_en": null,
    "source": "fimea_en_fi_terminology",
    "source_page_fi": 109,
    "official_ich_glossary_entry": false
  },
  {
    "id": "ich-e6-r3-term-136",
    "entry_type": "translation_mapping",
    "term_en": "protocol amendment",
    "preferred_label_fi": "tutkimussuunnitelman muutos",
    "definition_fi": null,
    "definition_en": null,
    "source": "fimea_en_fi_terminology",
    "source_page_fi": 109,
    "official_ich_glossary_entry": false
  },
  {
    "id": "ich-e6-r3-term-137",
    "entry_type": "translation_mapping",
    "term_en": "provision",
    "preferred_label_fi": "vaatimus, määräys, säännös",
    "definition_fi": null,
    "definition_en": null,
    "source": "fimea_en_fi_terminology",
    "source_page_fi": 109,
    "official_ich_glossary_entry": false
  },
  {
    "id": "ich-e6-r3-term-138",
    "entry_type": "translation_mapping",
    "term_en": "quality assurance (QA)",
    "preferred_label_fi": "laadunvarmistus",
    "definition_fi": null,
    "definition_en": null,
    "source": "fimea_en_fi_terminology",
    "source_page_fi": 109,
    "official_ich_glossary_entry": false
  },
  {
    "id": "ich-e6-r3-term-139",
    "entry_type": "translation_mapping",
    "term_en": "quality by design",
    "preferred_label_fi": "laadun suunnittelu",
    "definition_fi": null,
    "definition_en": null,
    "source": "fimea_en_fi_terminology",
    "source_page_fi": 109,
    "official_ich_glossary_entry": false
  },
  {
    "id": "ich-e6-r3-term-140",
    "entry_type": "translation_mapping",
    "term_en": "quality control (QC)",
    "preferred_label_fi": "laadunvalvonta",
    "definition_fi": null,
    "definition_en": null,
    "source": "fimea_en_fi_terminology",
    "source_page_fi": 109,
    "official_ich_glossary_entry": false
  },
  {
    "id": "ich-e6-r3-term-141",
    "entry_type": "translation_mapping",
    "term_en": "quality culture",
    "preferred_label_fi": "laatukulttuuri",
    "definition_fi": null,
    "definition_en": null,
    "source": "fimea_en_fi_terminology",
    "source_page_fi": 109,
    "official_ich_glossary_entry": false
  },
  {
    "id": "ich-e6-r3-term-142",
    "entry_type": "translation_mapping",
    "term_en": "quality tolerance limits",
    "preferred_label_fi": "laatutoleranssirajat",
    "definition_fi": null,
    "definition_en": null,
    "source": "fimea_en_fi_terminology",
    "source_page_fi": 109,
    "official_ich_glossary_entry": false
  },
  {
    "id": "ich-e6-r3-term-143",
    "entry_type": "translation_mapping",
    "term_en": "query",
    "preferred_label_fi": "tarkistuspyyntö",
    "definition_fi": null,
    "definition_en": null,
    "source": "fimea_en_fi_terminology",
    "source_page_fi": 109,
    "official_ich_glossary_entry": false
  },
  {
    "id": "ich-e6-r3-term-144",
    "entry_type": "translation_mapping",
    "term_en": "query resolution",
    "preferred_label_fi": "selvitetty tarkistuspyyntö",
    "definition_fi": null,
    "definition_en": null,
    "source": "fimea_en_fi_terminology",
    "source_page_fi": 109,
    "official_ich_glossary_entry": false
  },
  {
    "id": "ich-e6-r3-term-145",
    "entry_type": "translation_mapping",
    "term_en": "randomization",
    "preferred_label_fi": "satunnaistaminen",
    "definition_fi": null,
    "definition_en": null,
    "source": "fimea_en_fi_terminology",
    "source_page_fi": 109,
    "official_ich_glossary_entry": false
  },
  {
    "id": "ich-e6-r3-term-146",
    "entry_type": "translation_mapping",
    "term_en": "real-world source",
    "preferred_label_fi": "tosielämän tietolähde",
    "definition_fi": null,
    "definition_en": null,
    "source": "fimea_en_fi_terminology",
    "source_page_fi": 109,
    "official_ich_glossary_entry": false
  },
  {
    "id": "ich-e6-r3-term-147",
    "entry_type": "translation_mapping",
    "term_en": "reconciliation",
    "preferred_label_fi": "ristiintarkistus",
    "definition_fi": null,
    "definition_en": null,
    "source": "fimea_en_fi_terminology",
    "source_page_fi": 109,
    "official_ich_glossary_entry": false
  },
  {
    "id": "ich-e6-r3-term-148",
    "entry_type": "translation_mapping",
    "term_en": "record",
    "preferred_label_fi": "tallenne",
    "definition_fi": null,
    "definition_en": null,
    "source": "fimea_en_fi_terminology",
    "source_page_fi": 109,
    "official_ich_glossary_entry": false
  },
  {
    "id": "ich-e6-r3-term-149",
    "entry_type": "translation_mapping",
    "term_en": "recruit",
    "preferred_label_fi": "rekrytoida",
    "definition_fi": null,
    "definition_en": null,
    "source": "fimea_en_fi_terminology",
    "source_page_fi": 109,
    "official_ich_glossary_entry": false
  },
  {
    "id": "ich-e6-r3-term-150",
    "entry_type": "translation_mapping",
    "term_en": "reference dosage form",
    "preferred_label_fi": "vertailuannostelumuoto",
    "definition_fi": null,
    "definition_en": null,
    "source": "fimea_en_fi_terminology",
    "source_page_fi": 109,
    "official_ich_glossary_entry": false
  },
  {
    "id": "ich-e6-r3-term-151",
    "entry_type": "translation_mapping",
    "term_en": "reference point",
    "preferred_label_fi": "viitekohta",
    "definition_fi": null,
    "definition_en": null,
    "source": "fimea_en_fi_terminology",
    "source_page_fi": 110,
    "official_ich_glossary_entry": false
  },
  {
    "id": "ich-e6-r3-term-152",
    "entry_type": "translation_mapping",
    "term_en": "reference safety information (RSI)",
    "preferred_label_fi": "turvallisuutta koskevat viitetiedot (RSI)",
    "definition_fi": null,
    "definition_en": null,
    "source": "fimea_en_fi_terminology",
    "source_page_fi": 110,
    "official_ich_glossary_entry": false
  },
  {
    "id": "ich-e6-r3-term-153",
    "entry_type": "translation_mapping",
    "term_en": "regulatory authorities",
    "preferred_label_fi": "valvontaviranomaiset",
    "definition_fi": null,
    "definition_en": null,
    "source": "fimea_en_fi_terminology",
    "source_page_fi": 110,
    "official_ich_glossary_entry": false
  },
  {
    "id": "ich-e6-r3-term-154",
    "entry_type": "translation_mapping",
    "term_en": "regulatory requirements, applicable regulatory requirements",
    "preferred_label_fi": "lainsäädännön vaatimukset",
    "definition_fi": null,
    "definition_en": null,
    "source": "fimea_en_fi_terminology",
    "source_page_fi": 110,
    "official_ich_glossary_entry": false
  },
  {
    "id": "ich-e6-r3-term-155",
    "entry_type": "translation_mapping",
    "term_en": "repository",
    "preferred_label_fi": "tietokanta, tallennuspaikka, arkisto",
    "definition_fi": null,
    "definition_en": null,
    "source": "fimea_en_fi_terminology",
    "source_page_fi": 110,
    "official_ich_glossary_entry": false
  },
  {
    "id": "ich-e6-r3-term-156",
    "entry_type": "translation_mapping",
    "term_en": "rescue medication",
    "preferred_label_fi": "tutkimussuunnitelman mukaisesti otettava (hätä)lääke",
    "definition_fi": null,
    "definition_en": null,
    "source": "fimea_en_fi_terminology",
    "source_page_fi": 110,
    "official_ich_glossary_entry": false
  },
  {
    "id": "ich-e6-r3-term-157",
    "entry_type": "translation_mapping",
    "term_en": "reversibility",
    "preferred_label_fi": "palautuvuus",
    "definition_fi": null,
    "definition_en": null,
    "source": "fimea_en_fi_terminology",
    "source_page_fi": 110,
    "official_ich_glossary_entry": false
  },
  {
    "id": "ich-e6-r3-term-158",
    "entry_type": "translation_mapping",
    "term_en": "revised",
    "preferred_label_fi": "päivitetty",
    "definition_fi": null,
    "definition_en": null,
    "source": "fimea_en_fi_terminology",
    "source_page_fi": 110,
    "official_ich_glossary_entry": false
  },
  {
    "id": "ich-e6-r3-term-159",
    "entry_type": "translation_mapping",
    "term_en": "risk based strategies",
    "preferred_label_fi": "riskiperusteinen strategia",
    "definition_fi": null,
    "definition_en": null,
    "source": "fimea_en_fi_terminology",
    "source_page_fi": 110,
    "official_ich_glossary_entry": false
  },
  {
    "id": "ich-e6-r3-term-160",
    "entry_type": "translation_mapping",
    "term_en": "risk-benefit assessment",
    "preferred_label_fi": "riskien ja hyötyjen arviointi",
    "definition_fi": null,
    "definition_en": null,
    "source": "fimea_en_fi_terminology",
    "source_page_fi": 110,
    "official_ich_glossary_entry": false
  },
  {
    "id": "ich-e6-r3-term-161",
    "entry_type": "translation_mapping",
    "term_en": "risk management",
    "preferred_label_fi": "riskienhallinta",
    "definition_fi": null,
    "definition_en": null,
    "source": "fimea_en_fi_terminology",
    "source_page_fi": 110,
    "official_ich_glossary_entry": false
  },
  {
    "id": "ich-e6-r3-term-162",
    "entry_type": "translation_mapping",
    "term_en": "risk mitigation",
    "preferred_label_fi": "riskien vähentäminen",
    "definition_fi": null,
    "definition_en": null,
    "source": "fimea_en_fi_terminology",
    "source_page_fi": 110,
    "official_ich_glossary_entry": false
  },
  {
    "id": "ich-e6-r3-term-163",
    "entry_type": "translation_mapping",
    "term_en": "root cause analysis",
    "preferred_label_fi": "juurisyyanalyysi",
    "definition_fi": null,
    "definition_en": null,
    "source": "fimea_en_fi_terminology",
    "source_page_fi": 110,
    "official_ich_glossary_entry": false
  },
  {
    "id": "ich-e6-r3-term-164",
    "entry_type": "translation_mapping",
    "term_en": "route of administration",
    "preferred_label_fi": "antoreitti",
    "definition_fi": null,
    "definition_en": null,
    "source": "fimea_en_fi_terminology",
    "source_page_fi": 110,
    "official_ich_glossary_entry": false
  },
  {
    "id": "ich-e6-r3-term-165",
    "entry_type": "translation_mapping",
    "term_en": "SAE reconciliation",
    "preferred_label_fi": "Vakavien haittatapahtumien (SAE) tietojen ristiintarkistus",
    "definition_fi": null,
    "definition_en": null,
    "source": "fimea_en_fi_terminology",
    "source_page_fi": 110,
    "official_ich_glossary_entry": false
  },
  {
    "id": "ich-e6-r3-term-166",
    "entry_type": "translation_mapping",
    "term_en": "safety monitoring",
    "preferred_label_fi": "turvallisuusseuranta",
    "definition_fi": null,
    "definition_en": null,
    "source": "fimea_en_fi_terminology",
    "source_page_fi": 110,
    "official_ich_glossary_entry": false
  },
  {
    "id": "ich-e6-r3-term-167",
    "entry_type": "translation_mapping",
    "term_en": "sample size",
    "preferred_label_fi": "otoskoko",
    "definition_fi": null,
    "definition_en": null,
    "source": "fimea_en_fi_terminology",
    "source_page_fi": 110,
    "official_ich_glossary_entry": false
  },
  {
    "id": "ich-e6-r3-term-168",
    "entry_type": "translation_mapping",
    "term_en": "screening log",
    "preferred_label_fi": "lista seulotuista osallistujista",
    "definition_fi": null,
    "definition_en": null,
    "source": "fimea_en_fi_terminology",
    "source_page_fi": 110,
    "official_ich_glossary_entry": false
  },
  {
    "id": "ich-e6-r3-term-169",
    "entry_type": "translation_mapping",
    "term_en": "serious adverse event (SAE)",
    "preferred_label_fi": "vakava haittatapahtuma (SAE)",
    "definition_fi": null,
    "definition_en": null,
    "source": "fimea_en_fi_terminology",
    "source_page_fi": 110,
    "official_ich_glossary_entry": false
  },
  {
    "id": "ich-e6-r3-term-170",
    "entry_type": "translation_mapping",
    "term_en": "service provider",
    "preferred_label_fi": "palveluntarjoaja",
    "definition_fi": null,
    "definition_en": null,
    "source": "fimea_en_fi_terminology",
    "source_page_fi": 110,
    "official_ich_glossary_entry": false
  },
  {
    "id": "ich-e6-r3-term-171",
    "entry_type": "translation_mapping",
    "term_en": "signature",
    "preferred_label_fi": "allekirjoitus",
    "definition_fi": null,
    "definition_en": null,
    "source": "fimea_en_fi_terminology",
    "source_page_fi": 110,
    "official_ich_glossary_entry": false
  },
  {
    "id": "ich-e6-r3-term-172",
    "entry_type": "translation_mapping",
    "term_en": "source data",
    "preferred_label_fi": "lähdetiedot",
    "definition_fi": null,
    "definition_en": null,
    "source": "fimea_en_fi_terminology",
    "source_page_fi": 110,
    "official_ich_glossary_entry": false
  },
  {
    "id": "ich-e6-r3-term-173",
    "entry_type": "translation_mapping",
    "term_en": "source records",
    "preferred_label_fi": "lähdetallenteet",
    "definition_fi": null,
    "definition_en": null,
    "source": "fimea_en_fi_terminology",
    "source_page_fi": 110,
    "official_ich_glossary_entry": false
  },
  {
    "id": "ich-e6-r3-term-174",
    "entry_type": "translation_mapping",
    "term_en": "species",
    "preferred_label_fi": "laji",
    "definition_fi": null,
    "definition_en": null,
    "source": "fimea_en_fi_terminology",
    "source_page_fi": 110,
    "official_ich_glossary_entry": false
  },
  {
    "id": "ich-e6-r3-term-175",
    "entry_type": "translation_mapping",
    "term_en": "sponsor",
    "preferred_label_fi": "toimeksiantaja",
    "definition_fi": null,
    "definition_en": null,
    "source": "fimea_en_fi_terminology",
    "source_page_fi": 110,
    "official_ich_glossary_entry": false
  },
  {
    "id": "ich-e6-r3-term-176",
    "entry_type": "translation_mapping",
    "term_en": "sponsor-investigator",
    "preferred_label_fi": "toimeksiantaja-tutkija",
    "definition_fi": null,
    "definition_en": null,
    "source": "fimea_en_fi_terminology",
    "source_page_fi": 110,
    "official_ich_glossary_entry": false
  },
  {
    "id": "ich-e6-r3-term-177",
    "entry_type": "translation_mapping",
    "term_en": "standard operating procedure (SOP)",
    "preferred_label_fi": "vakioitu toimintaohje (SOP)",
    "definition_fi": null,
    "definition_en": null,
    "source": "fimea_en_fi_terminology",
    "source_page_fi": 110,
    "official_ich_glossary_entry": false
  },
  {
    "id": "ich-e6-r3-term-178",
    "entry_type": "translation_mapping",
    "term_en": "sub-investigator",
    "preferred_label_fi": "avustava tutkija",
    "definition_fi": null,
    "definition_en": null,
    "source": "fimea_en_fi_terminology",
    "source_page_fi": 110,
    "official_ich_glossary_entry": false
  },
  {
    "id": "ich-e6-r3-term-179",
    "entry_type": "translation_mapping",
    "term_en": "suspected unexpected serious adverse reaction (SUSAR)",
    "preferred_label_fi": "epäilty odottamaton vakava haittavaikutus (SUSAR)",
    "definition_fi": null,
    "definition_en": null,
    "source": "fimea_en_fi_terminology",
    "source_page_fi": 110,
    "official_ich_glossary_entry": false
  },
  {
    "id": "ich-e6-r3-term-180",
    "entry_type": "translation_mapping",
    "term_en": "system defect",
    "preferred_label_fi": "järjestelmävirhe",
    "definition_fi": null,
    "definition_en": null,
    "source": "fimea_en_fi_terminology",
    "source_page_fi": 110,
    "official_ich_glossary_entry": false
  },
  {
    "id": "ich-e6-r3-term-181",
    "entry_type": "translation_mapping",
    "term_en": "systemic distribution",
    "preferred_label_fi": "jakautuminen elimistössä / systeeminen jakautuminen",
    "definition_fi": null,
    "definition_en": null,
    "source": "fimea_en_fi_terminology",
    "source_page_fi": 110,
    "official_ich_glossary_entry": false
  },
  {
    "id": "ich-e6-r3-term-182",
    "entry_type": "translation_mapping",
    "term_en": "terminal medical records",
    "preferred_label_fi": "kuolintodistus",
    "definition_fi": null,
    "definition_en": null,
    "source": "fimea_en_fi_terminology",
    "source_page_fi": 110,
    "official_ich_glossary_entry": false
  },
  {
    "id": "ich-e6-r3-term-183",
    "entry_type": "translation_mapping",
    "term_en": "trial conduct",
    "preferred_label_fi": "lääketutkimuksen organisointi, toteuttaminen tai suorittaminen",
    "definition_fi": null,
    "definition_en": null,
    "source": "fimea_en_fi_terminology",
    "source_page_fi": 110,
    "official_ich_glossary_entry": false
  },
  {
    "id": "ich-e6-r3-term-184",
    "entry_type": "translation_mapping",
    "term_en": "trial master file",
    "preferred_label_fi": "lääketutkimuksen kantatiedosto",
    "definition_fi": null,
    "definition_en": null,
    "source": "fimea_en_fi_terminology",
    "source_page_fi": 110,
    "official_ich_glossary_entry": false
  },
  {
    "id": "ich-e6-r3-term-185",
    "entry_type": "translation_mapping",
    "term_en": "trial participant",
    "preferred_label_fi": "tutkimukseen osallistuja",
    "definition_fi": null,
    "definition_en": null,
    "source": "fimea_en_fi_terminology",
    "source_page_fi": 110,
    "official_ich_glossary_entry": false
  },
  {
    "id": "ich-e6-r3-term-186",
    "entry_type": "translation_mapping",
    "term_en": "trial participant identification code",
    "preferred_label_fi": "tutkimukseen osallistujan tunnistekoodi",
    "definition_fi": null,
    "definition_en": null,
    "source": "fimea_en_fi_terminology",
    "source_page_fi": 110,
    "official_ich_glossary_entry": false
  },
  {
    "id": "ich-e6-r3-term-187",
    "entry_type": "translation_mapping",
    "term_en": "unbiased",
    "preferred_label_fi": "harhaton",
    "definition_fi": null,
    "definition_en": null,
    "source": "fimea_en_fi_terminology",
    "source_page_fi": 110,
    "official_ich_glossary_entry": false
  },
  {
    "id": "ich-e6-r3-term-188",
    "entry_type": "translation_mapping",
    "term_en": "unblinding",
    "preferred_label_fi": "sokkoutuksen purkaminen",
    "definition_fi": null,
    "definition_en": null,
    "source": "fimea_en_fi_terminology",
    "source_page_fi": 110,
    "official_ich_glossary_entry": false
  },
  {
    "id": "ich-e6-r3-term-189",
    "entry_type": "translation_mapping",
    "term_en": "unfavourable and unintended effect",
    "preferred_label_fi": "epäsuotuisa ja tahaton vaikutus",
    "definition_fi": null,
    "definition_en": null,
    "source": "fimea_en_fi_terminology",
    "source_page_fi": 111,
    "official_ich_glossary_entry": false
  },
  {
    "id": "ich-e6-r3-term-190",
    "entry_type": "translation_mapping",
    "term_en": "unfavourable medical event",
    "preferred_label_fi": "(tutkimuksen kannalta) epäsuotuisa lääketieteellinen\ntapahtuma",
    "definition_fi": null,
    "definition_en": null,
    "source": "fimea_en_fi_terminology",
    "source_page_fi": 111,
    "official_ich_glossary_entry": false
  },
  {
    "id": "ich-e6-r3-term-191",
    "entry_type": "translation_mapping",
    "term_en": "unit dose",
    "preferred_label_fi": "kerta-annos",
    "definition_fi": null,
    "definition_en": null,
    "source": "fimea_en_fi_terminology",
    "source_page_fi": 111,
    "official_ich_glossary_entry": false
  },
  {
    "id": "ich-e6-r3-term-192",
    "entry_type": "translation_mapping",
    "term_en": "validation status",
    "preferred_label_fi": "validoinnin tila",
    "definition_fi": null,
    "definition_en": null,
    "source": "fimea_en_fi_terminology",
    "source_page_fi": 111,
    "official_ich_glossary_entry": false
  },
  {
    "id": "ich-e6-r3-term-193",
    "entry_type": "translation_mapping",
    "term_en": "validity",
    "preferred_label_fi": "pätevyys",
    "definition_fi": null,
    "definition_en": null,
    "source": "fimea_en_fi_terminology",
    "source_page_fi": 111,
    "official_ich_glossary_entry": false
  },
  {
    "id": "ich-e6-r3-term-194",
    "entry_type": "translation_mapping",
    "term_en": "vulnerable participant",
    "preferred_label_fi": "haavoittuvassa asemassa oleva osallistuja",
    "definition_fi": null,
    "definition_en": null,
    "source": "fimea_en_fi_terminology",
    "source_page_fi": 111,
    "official_ich_glossary_entry": false
  }
]
